pycppstreams/__init__.py
pycppstreams-0.0.2.dist-info/METADATA
pycppstreams-0.0.2.dist-info/WHEEL
pycppstreams-0.0.2.dist-info/top_level.txt
pycppstreams-0.0.2.dist-info/RECORD
