Metadata-Version: 2.1
Name: pycppstreams
Version: 0.0.2
Summary: A C++ style stream library for Python
Home-page: https://pypi.org
Author: dianbtcmputr
Author-email: 3663144423@qq.com
Classifier: Programming Language :: Python :: 3
Classifier: License :: OSI Approved :: MIT License
Classifier: Operating System :: OS Independent
Requires: pyttsx4
Requires-Dist: pyttsx4
